{
	"date":"03-11-2015T14:00:00.0Z",
	"user":"http://cf.delek.org/planeguy",
	"post":{
		"url":"http://cf.delek.org/planeguy/posts/1",
		"relates":{
			"replies-to":{
				"post":"http://google.com/drive/pixelante/cf/post0006.json",
				"by":"http://google.com/drive/pixelante/cf/me.json"
			},
			"tags":[
				"http://cf.delek.org/chanceula"
			],
			"shares":{
				"post":"http://google.com/drive/pixelante/cf/post0006.json",
				"by":"http://google.com/drive/pixelante/cf/me.json"
			}"
		},
		"content":"STUFF"
	}
}